AetherLog/__init__.py
AetherLog/levels.py
AetherLog/main.py
AetherLog/models.py
aetherlog-1.1.0.dist-info/LICENSE
aetherlog-1.1.0.dist-info/METADATA
aetherlog-1.1.0.dist-info/WHEEL
aetherlog-1.1.0.dist-info/top_level.txt
aetherlog-1.1.0.dist-info/RECORD
