Metadata-Version: 2.2
Name: aetherlog
Version: 1.1.0
Summary: Python logging library
Author-email: v4nixd <v4nixdmail@gmail.com>
License: MIT
Project-URL: Homepage, https://github.com/v4nixd/AetherLog
Project-URL: Bug Tracker, https://github.com/v4nixd/AetherLog/issues
License-File: LICENSE
Requires-Dist: rich
